sciscripts/__init__.py
sciscripts/Analysis/ABRs.py
sciscripts/Analysis/Analysis.py
sciscripts/Analysis/CalciumImaging.py
sciscripts/Analysis/Comodulation.py
sciscripts/Analysis/DLC.py
sciscripts/Analysis/ERPs.py
sciscripts/Analysis/GPIAS.py
sciscripts/Analysis/Images.py
sciscripts/Analysis/SoundMeasurements.py
sciscripts/Analysis/Stats.py
sciscripts/Analysis/Treadmill.py
sciscripts/Analysis/Videos.py
sciscripts/Analysis/__init__.py
sciscripts/Analysis/Plot/ABRs.py
sciscripts/Analysis/Plot/CalciumImaging.py
sciscripts/Analysis/Plot/ERPs.py
sciscripts/Analysis/Plot/GPIAS.py
sciscripts/Analysis/Plot/Klusta.py
sciscripts/Analysis/Plot/Plot.py
sciscripts/Analysis/Plot/SoundMeasurements.py
sciscripts/Analysis/Plot/Stats.py
sciscripts/Analysis/Plot/Treadmill.py
sciscripts/Analysis/Plot/Units.py
sciscripts/Analysis/Plot/WaveClus.py
sciscripts/Analysis/Plot/__init__.py
sciscripts/Analysis/Units/Circus.py
sciscripts/Analysis/Units/Klusta.py
sciscripts/Analysis/Units/Units.py
sciscripts/Analysis/Units/WaveClus.py
sciscripts/Analysis/Units/__init__.py
sciscripts/Exps/AcousticNoiseTrauma.py
sciscripts/Exps/Arduino.py
sciscripts/Exps/GPIAS.py
sciscripts/Exps/SoundAndLaserStimulation.py
sciscripts/Exps/SoundCard.py
sciscripts/Exps/SoundMeasurements.py
sciscripts/Exps/__init__.py
sciscripts/IO/Arduino.py
sciscripts/IO/Asdf.py
sciscripts/IO/Bin.py
sciscripts/IO/DAqs.py
sciscripts/IO/Hdf5.py
sciscripts/IO/IO.py
sciscripts/IO/Intan.py
sciscripts/IO/Json.py
sciscripts/IO/Klusta.py
sciscripts/IO/Mat.py
sciscripts/IO/MouseProfilerTracker.py
sciscripts/IO/SigGen.py
sciscripts/IO/SoundCard.py
sciscripts/IO/Tar.py
sciscripts/IO/Txt.py
sciscripts/IO/Video.py
sciscripts/IO/Wav.py
sciscripts/IO/WaveClus.py
sciscripts/IO/XML.py
sciscripts/IO/__init__.py
sciscripts/IO/OpenEphys/Binary.py
sciscripts/IO/OpenEphys/OpenEphys.py
sciscripts/IO/OpenEphys/OpenEphysFormat.py
sciscripts/IO/OpenEphys/SettingsXML.py
sciscripts/IO/OpenEphys/__init__.py
sciscripts-3.3.1.dist-info/LICENSE
sciscripts-3.3.1.dist-info/METADATA
sciscripts-3.3.1.dist-info/WHEEL
sciscripts-3.3.1.dist-info/top_level.txt
sciscripts-3.3.1.dist-info/RECORD
